livekit/plugins/rtzr/__init__.py
livekit/plugins/rtzr/log.py
livekit/plugins/rtzr/rtzrapi.py
livekit/plugins/rtzr/stt.py
livekit/plugins/rtzr/version.py
livekit_plugins_rtzr-1.3.11.dist-info/METADATA
livekit_plugins_rtzr-1.3.11.dist-info/WHEEL
livekit_plugins_rtzr-1.3.11.dist-info/RECORD
