Metadata-Version: 2.4
Name: livekit-plugins-rtzr
Version: 1.3.11
Summary: Agent Framework plugin for RTZR Streaming STT
Project-URL: Documentation, https://docs.livekit.io
Project-URL: Website, https://livekit.io/
Project-URL: Source, https://github.com/livekit/agents
Author-email: RTZR <support@rtzr.ai>
License-Expression: Apache-2.0
Keywords: audio,livekit,realtime,rtzr,speech-to-text,video,webrtc
Classifier: Intended Audience :: Developers
Classifier: License :: OSI Approved :: Apache Software License
Classifier: Programming Language :: Python :: 3
Classifier: Programming Language :: Python :: 3 :: Only
Classifier: Programming Language :: Python :: 3.9
Classifier: Programming Language :: Python :: 3.10
Classifier: Topic :: Multimedia :: Sound/Audio
Classifier: Topic :: Multimedia :: Video
Classifier: Topic :: Scientific/Engineering :: Artificial Intelligence
Requires-Python: >=3.9.0
Requires-Dist: aiohttp>=3.9.0
Requires-Dist: httpx>=0.24.0
Requires-Dist: livekit-agents>=1.3.11
